azure/mgmt/portalservicescopilot/__init__.py
azure/mgmt/portalservicescopilot/_client.py
azure/mgmt/portalservicescopilot/_configuration.py
azure/mgmt/portalservicescopilot/_model_base.py
azure/mgmt/portalservicescopilot/_patch.py
azure/mgmt/portalservicescopilot/_serialization.py
azure/mgmt/portalservicescopilot/_version.py
azure/mgmt/portalservicescopilot/py.typed
azure/mgmt/portalservicescopilot/aio/__init__.py
azure/mgmt/portalservicescopilot/aio/_client.py
azure/mgmt/portalservicescopilot/aio/_configuration.py
azure/mgmt/portalservicescopilot/aio/_patch.py
azure/mgmt/portalservicescopilot/aio/operations/__init__.py
azure/mgmt/portalservicescopilot/aio/operations/_operations.py
azure/mgmt/portalservicescopilot/aio/operations/_patch.py
azure/mgmt/portalservicescopilot/models/__init__.py
azure/mgmt/portalservicescopilot/models/_enums.py
azure/mgmt/portalservicescopilot/models/_models.py
azure/mgmt/portalservicescopilot/models/_patch.py
azure/mgmt/portalservicescopilot/operations/__init__.py
azure/mgmt/portalservicescopilot/operations/_operations.py
azure/mgmt/portalservicescopilot/operations/_patch.py
azure_mgmt_portalservicescopilot-1.0.0b1.dist-info/LICENSE
azure_mgmt_portalservicescopilot-1.0.0b1.dist-info/METADATA
azure_mgmt_portalservicescopilot-1.0.0b1.dist-info/WHEEL
azure_mgmt_portalservicescopilot-1.0.0b1.dist-info/top_level.txt
azure_mgmt_portalservicescopilot-1.0.0b1.dist-info/RECORD
